bentoudev/dataclass/__init__.py
bentoudev/dataclass/_version.py
bentoudev/dataclass/base.py
bentoudev/dataclass/json_schema.py
bentoudev/dataclass/yaml_loader.py
bentoudev.dataclass-1.6.0.dist-info/METADATA
bentoudev.dataclass-1.6.0.dist-info/WHEEL
bentoudev.dataclass-1.6.0.dist-info/top_level.txt
bentoudev.dataclass-1.6.0.dist-info/RECORD
